LICENSE
README.md
pyproject.toml
setup.cfg
setup.py
hurricaneapi/__init__.py
hurricaneapi/application.py
hurricaneapi.egg-info/PKG-INFO
hurricaneapi.egg-info/SOURCES.txt
hurricaneapi.egg-info/dependency_links.txt
hurricaneapi.egg-info/not-zip-safe
hurricaneapi.egg-info/requires.txt
hurricaneapi.egg-info/top_level.txt
hurricaneapi/middleware/__init__.py
hurricaneapi/middleware/base_middleware.py
hurricaneapi/middleware/cors_middleware.py
hurricaneapi/middleware/trusted_host_middleware.py
hurricaneapi/responses/__init__.py
hurricaneapi/responses/file_response.py
hurricaneapi/responses/html_response.py
hurricaneapi/responses/json_response.py
hurricaneapi/responses/plain_text_response.py
hurricaneapi/responses/redirect_response.py
hurricaneapi/responses/response.py
hurricaneapi/routing/__init__.py
hurricaneapi/routing/route.py
hurricaneapi/routing/router.py