Metadata-Version: 2.1
Name: hurricaneapi
Version: 0.1.8
Summary: Hurricaneapi framework
Home-page: https://github.com/daniil49926/hurricaneapi
Author: Shchipko Daniil
Author-email: daniil49925@ya.ru
License: MIT
Platform: UNKNOWN
License-File: LICENSE
